sinagot/__init__.py
sinagot/base.py
sinagot/config.py
sinagot/logger.py
sinagot/node.py
sinagot/path_template.py
sinagot/py.typed
sinagot/ray.py
sinagot/storage.py
sinagot/workflow.py
sinagot/workspace.py
sinagot-0.5.3.dist-info/entry_points.txt
sinagot-0.5.3.dist-info/LICENSE
sinagot-0.5.3.dist-info/WHEEL
sinagot-0.5.3.dist-info/METADATA
sinagot-0.5.3.dist-info/RECORD
