Metadata-Version: 2.1
Name: sinagot
Version: 0.5.3
Summary: Python lightweight workflow management framework with data exploration features
Home-page: https://gitlab.com/YannBeauxis/sinagot
License: BSD-2-Clause
Author: Yann Beauxis
Author-email: pro@yannbeauxis.net
Maintainer: Yann Beauxis
Maintainer-email: pro@yannbeauxis.net
Requires-Python: >=3.8,<4.0
Classifier: License :: OSI Approved :: BSD License
Classifier: Programming Language :: Python :: 3
Classifier: Programming Language :: Python :: 3.10
Classifier: Programming Language :: Python :: 3.8
Classifier: Programming Language :: Python :: 3.9
Requires-Dist: pandas (>=1.3.5,<2.0.0)
Requires-Dist: pydantic (>=1.9.0,<2.0.0)
Requires-Dist: ray (>=1.9.1,<2.0.0)
Project-URL: Documentation, https://gitlab.com/YannBeauxis/sinagot
Project-URL: Repository, https://gitlab.com/YannBeauxis/sinagot
